<?xml version="1.0"?>
<!DOCTYPE hibernate-mapping PUBLIC "-//Hibernate/Hibernate Mapping DTD 3.0//EN"
"F://workspace/supermarket/src/dtd/hibernate-mapping-3.0.dtd">
<!-- Generated 2015-4-13 10:16:13 by Hibernate Tools 3.4.0.CR1 -->
<hibernate-mapping>
    <class name="cuit.edu.BEAN.Depot" table="depot" catalog="supermarket">
        <id name="id" type="int">
            <column name="id" />
            <generator class="assigned" />
        </id>
        <property name="manage" type="string">
            <column name="manage" length="50" />
        </property>
        <property name="functional" type="string">
            <column name="functional" length="200" />
        </property>
    </class>
</hibernate-mapping>
